[
    {
        "line": "20",
        "column": "8",
        "severity": "warning",
        "message": "Unused import - java.io.IOException.",
        "source": "com.puppycrawl.tools.checkstyle.checks.imports.UnusedImportsCheck"
    },
    {
        "line": "22",
        "column": "8",
        "severity": "warning",
        "message": "Unused import - java.util.Collections.",
        "source": "com.puppycrawl.tools.checkstyle.checks.imports.UnusedImportsCheck"
    },
    {
        "line": "23",
        "column": "8",
        "severity": "warning",
        "message": "Unused import - java.util.HashMap.",
        "source": "com.puppycrawl.tools.checkstyle.checks.imports.UnusedImportsCheck"
    },
    {
        "line": "24",
        "column": "8",
        "severity": "warning",
        "message": "Unused import - java.util.Map.",
        "source": "com.puppycrawl.tools.checkstyle.checks.imports.UnusedImportsCheck"
    },
    {
        "line": "28",
        "column": "8",
        "severity": "warning",
        "message": "Unused import - org.apache.servicecomb.codec.protobuf.utils.schema.NotWrapSchema.",
        "source": "com.puppycrawl.tools.checkstyle.checks.imports.UnusedImportsCheck"
    },
    {
        "line": "33",
        "column": "8",
        "severity": "warning",
        "message": "Unused import - org.apache.servicecomb.foundation.vertx.client.tcp.TcpData.",
        "source": "com.puppycrawl.tools.checkstyle.checks.imports.UnusedImportsCheck"
    },
    {
        "line": "39",
        "column": "8",
        "severity": "warning",
        "message": "Unused import - org.apache.servicecomb.swagger.invocation.Response.",
        "source": "com.puppycrawl.tools.checkstyle.checks.imports.UnusedImportsCheck"
    },
    {
        "line": "41",
        "column": "8",
        "severity": "warning",
        "message": "Unused import - org.apache.servicecomb.transport.highway.message.ResponseHeader.",
        "source": "com.puppycrawl.tools.checkstyle.checks.imports.UnusedImportsCheck"
    },
    {
        "line": "50",
        "column": "8",
        "severity": "warning",
        "message": "Unused import - io.protostuff.Input.",
        "source": "com.puppycrawl.tools.checkstyle.checks.imports.UnusedImportsCheck"
    },
    {
        "line": "53",
        "column": "8",
        "severity": "warning",
        "message": "Unused import - mockit.Mock.",
        "source": "com.puppycrawl.tools.checkstyle.checks.imports.UnusedImportsCheck"
    },
    {
        "line": "54",
        "column": "8",
        "severity": "warning",
        "message": "Unused import - mockit.MockUp.",
        "source": "com.puppycrawl.tools.checkstyle.checks.imports.UnusedImportsCheck"
    },
    {
        "line": "197",
        "column": "35",
        "severity": "warning",
        "message": "'23432142' is a magic number.",
        "source": "com.puppycrawl.tools.checkstyle.checks.coding.MagicNumberCheck"
    },
    {
        "line": "211",
        "column": "80",
        "severity": "warning",
        "message": "'7' is a magic number.",
        "source": "com.puppycrawl.tools.checkstyle.checks.coding.MagicNumberCheck"
    }
]