[
    {
        "line": "0",
        "severity": "warning",
        "message": "Missing package-info.java file.",
        "source": "com.puppycrawl.tools.checkstyle.checks.javadoc.JavadocPackageCheck"
    },
    {
        "line": "21",
        "severity": "warning",
        "message": "Wrong order for 'org.apache.usergrid.ServiceITSetup' import.",
        "source": "com.puppycrawl.tools.checkstyle.checks.imports.ImportOrderCheck"
    },
    {
        "line": "36",
        "severity": "error",
        "message": "Using the '.*' form of import should be avoided - org.apache.usergrid.persistence.*.",
        "source": "com.puppycrawl.tools.checkstyle.checks.imports.AvoidStarImportCheck"
    },
    {
        "line": "38",
        "severity": "warning",
        "message": "'org.junit.BeforeClass' should be separated from previous imports.",
        "source": "com.puppycrawl.tools.checkstyle.checks.imports.ImportOrderCheck"
    },
    {
        "line": "45",
        "severity": "error",
        "message": "Using the '.*' form of import should be avoided - java.util.*.",
        "source": "com.puppycrawl.tools.checkstyle.checks.imports.AvoidStarImportCheck"
    },
    {
        "line": "45",
        "severity": "warning",
        "message": "Wrong order for 'java.util.*' import.",
        "source": "com.puppycrawl.tools.checkstyle.checks.imports.ImportOrderCheck"
    },
    {
        "line": "50",
        "severity": "error",
        "message": "Using the '.*' form of import should be avoided - org.junit.Assert.*.",
        "source": "com.puppycrawl.tools.checkstyle.checks.imports.AvoidStarImportCheck"
    },
    {
        "line": "75",
        "column": "40",
        "severity": "warning",
        "message": "Name 'setup' must match pattern '^([A-Z](_?[A-Z0-9]+)*)|(log)$'.",
        "source": "com.puppycrawl.tools.checkstyle.checks.naming.ConstantNameCheck"
    },
    {
        "line": "98",
        "severity": "warning",
        "message": "Line has trailing spaces.",
        "source": "com.puppycrawl.tools.checkstyle.checks.regexp.RegexpSinglelineCheck"
    },
    {
        "line": "138",
        "column": "26",
        "severity": "warning",
        "message": "Array brackets at illegal position.",
        "source": "com.puppycrawl.tools.checkstyle.checks.ArrayTypeStyleCheck"
    },
    {
        "line": "145",
        "column": "64",
        "severity": "warning",
        "message": "',' is not followed by whitespace.",
        "source": "com.puppycrawl.tools.checkstyle.checks.whitespace.WhitespaceAfterCheck"
    },
    {
        "line": "149",
        "severity": "warning",
        "message": "Line is longer than 120 characters (found 124).",
        "source": "com.puppycrawl.tools.checkstyle.checks.sizes.LineLengthCheck"
    },
    {
        "line": "150",
        "severity": "warning",
        "message": "Line is longer than 120 characters (found 125).",
        "source": "com.puppycrawl.tools.checkstyle.checks.sizes.LineLengthCheck"
    },
    {
        "line": "179",
        "column": "13",
        "severity": "warning",
        "message": "Empty statement.",
        "source": "com.puppycrawl.tools.checkstyle.checks.coding.EmptyStatementCheck"
    },
    {
        "line": "191",
        "column": "49",
        "severity": "warning",
        "message": "',' is not followed by whitespace.",
        "source": "com.puppycrawl.tools.checkstyle.checks.whitespace.WhitespaceAfterCheck"
    },
    {
        "line": "199",
        "column": "13",
        "severity": "warning",
        "message": "Empty statement.",
        "source": "com.puppycrawl.tools.checkstyle.checks.coding.EmptyStatementCheck"
    },
    {
        "line": "207",
        "column": "63",
        "severity": "warning",
        "message": "',' is not followed by whitespace.",
        "source": "com.puppycrawl.tools.checkstyle.checks.whitespace.WhitespaceAfterCheck"
    },
    {
        "line": "207",
        "column": "71",
        "severity": "warning",
        "message": "',' is not followed by whitespace.",
        "source": "com.puppycrawl.tools.checkstyle.checks.whitespace.WhitespaceAfterCheck"
    },
    {
        "line": "209",
        "column": "12",
        "severity": "warning",
        "message": "'for' is not followed by whitespace.",
        "source": "com.puppycrawl.tools.checkstyle.checks.whitespace.WhitespaceAroundCheck"
    },
    {
        "line": "209",
        "column": "26",
        "severity": "warning",
        "message": "':' is not preceded with whitespace.",
        "source": "com.puppycrawl.tools.checkstyle.checks.whitespace.WhitespaceAroundCheck"
    },
    {
        "line": "219",
        "column": "12",
        "severity": "warning",
        "message": "'for' is not followed by whitespace.",
        "source": "com.puppycrawl.tools.checkstyle.checks.whitespace.WhitespaceAroundCheck"
    },
    {
        "line": "219",
        "column": "18",
        "severity": "warning",
        "message": "'=' is not preceded with whitespace.",
        "source": "com.puppycrawl.tools.checkstyle.checks.whitespace.WhitespaceAroundCheck"
    },
    {
        "line": "219",
        "column": "19",
        "severity": "warning",
        "message": "'=' is not followed by whitespace.",
        "source": "com.puppycrawl.tools.checkstyle.checks.whitespace.WhitespaceAroundCheck"
    },
    {
        "line": "219",
        "column": "21",
        "severity": "warning",
        "message": "';' is not followed by whitespace.",
        "source": "com.puppycrawl.tools.checkstyle.checks.whitespace.WhitespaceAfterCheck"
    },
    {
        "line": "219",
        "column": "22",
        "severity": "warning",
        "message": "'<' is not preceded with whitespace.",
        "source": "com.puppycrawl.tools.checkstyle.checks.whitespace.WhitespaceAroundCheck"
    },
    {
        "line": "219",
        "column": "23",
        "severity": "warning",
        "message": "'<' is not followed by whitespace.",
        "source": "com.puppycrawl.tools.checkstyle.checks.whitespace.WhitespaceAroundCheck"
    },
    {
        "line": "219",
        "column": "25",
        "severity": "warning",
        "message": "';' is not followed by whitespace.",
        "source": "com.puppycrawl.tools.checkstyle.checks.whitespace.WhitespaceAfterCheck"
    },
    {
        "line": "227",
        "column": "9",
        "severity": "warning",
        "message": "Each variable declaration must be in its own statement.",
        "source": "com.puppycrawl.tools.checkstyle.checks.coding.MultipleVariableDeclarationsCheck"
    },
    {
        "line": "227",
        "column": "20",
        "severity": "warning",
        "message": "',' is not followed by whitespace.",
        "source": "com.puppycrawl.tools.checkstyle.checks.whitespace.WhitespaceAfterCheck"
    },
    {
        "line": "227",
        "column": "42",
        "severity": "warning",
        "message": "',' is not followed by whitespace.",
        "source": "com.puppycrawl.tools.checkstyle.checks.whitespace.WhitespaceAfterCheck"
    },
    {
        "line": "229",
        "column": "12",
        "severity": "warning",
        "message": "'for' is not followed by whitespace.",
        "source": "com.puppycrawl.tools.checkstyle.checks.whitespace.WhitespaceAroundCheck"
    },
    {
        "line": "229",
        "column": "18",
        "severity": "warning",
        "message": "'=' is not preceded with whitespace.",
        "source": "com.puppycrawl.tools.checkstyle.checks.whitespace.WhitespaceAroundCheck"
    },
    {
        "line": "229",
        "column": "19",
        "severity": "warning",
        "message": "'=' is not followed by whitespace.",
        "source": "com.puppycrawl.tools.checkstyle.checks.whitespace.WhitespaceAroundCheck"
    },
    {
        "line": "229",
        "column": "21",
        "severity": "warning",
        "message": "';' is not followed by whitespace.",
        "source": "com.puppycrawl.tools.checkstyle.checks.whitespace.WhitespaceAfterCheck"
    },
    {
        "line": "229",
        "column": "22",
        "severity": "warning",
        "message": "'<' is not preceded with whitespace.",
        "source": "com.puppycrawl.tools.checkstyle.checks.whitespace.WhitespaceAroundCheck"
    },
    {
        "line": "229",
        "column": "23",
        "severity": "warning",
        "message": "'<' is not followed by whitespace.",
        "source": "com.puppycrawl.tools.checkstyle.checks.whitespace.WhitespaceAroundCheck"
    },
    {
        "line": "229",
        "column": "25",
        "severity": "warning",
        "message": "';' is not followed by whitespace.",
        "source": "com.puppycrawl.tools.checkstyle.checks.whitespace.WhitespaceAfterCheck"
    },
    {
        "line": "232",
        "column": "54",
        "severity": "warning",
        "message": "',' is not followed by whitespace.",
        "source": "com.puppycrawl.tools.checkstyle.checks.whitespace.WhitespaceAfterCheck"
    },
    {
        "line": "233",
        "column": "54",
        "severity": "warning",
        "message": "',' is not followed by whitespace.",
        "source": "com.puppycrawl.tools.checkstyle.checks.whitespace.WhitespaceAfterCheck"
    },
    {
        "line": "235",
        "column": "15",
        "severity": "warning",
        "message": "'if' is not followed by whitespace.",
        "source": "com.puppycrawl.tools.checkstyle.checks.whitespace.WhitespaceAroundCheck"
    },
    {
        "line": "235",
        "column": "17",
        "severity": "warning",
        "message": "'==' is not preceded with whitespace.",
        "source": "com.puppycrawl.tools.checkstyle.checks.whitespace.WhitespaceAroundCheck"
    },
    {
        "line": "235",
        "column": "19",
        "severity": "warning",
        "message": "'==' is not followed by whitespace.",
        "source": "com.puppycrawl.tools.checkstyle.checks.whitespace.WhitespaceAroundCheck"
    },
    {
        "line": "237",
        "column": "49",
        "severity": "warning",
        "message": "',' is not followed by whitespace.",
        "source": "com.puppycrawl.tools.checkstyle.checks.whitespace.WhitespaceAfterCheck"
    },
    {
        "line": "238",
        "column": "49",
        "severity": "warning",
        "message": "',' is not followed by whitespace.",
        "source": "com.puppycrawl.tools.checkstyle.checks.whitespace.WhitespaceAfterCheck"
    },
    {
        "line": "274",
        "column": "13",
        "severity": "warning",
        "message": "Empty statement.",
        "source": "com.puppycrawl.tools.checkstyle.checks.coding.EmptyStatementCheck"
    },
    {
        "line": "286",
        "column": "49",
        "severity": "warning",
        "message": "',' is not followed by whitespace.",
        "source": "com.puppycrawl.tools.checkstyle.checks.whitespace.WhitespaceAfterCheck"
    },
    {
        "line": "294",
        "column": "13",
        "severity": "warning",
        "message": "Empty statement.",
        "source": "com.puppycrawl.tools.checkstyle.checks.coding.EmptyStatementCheck"
    },
    {
        "line": "303",
        "column": "14",
        "severity": "warning",
        "message": "'while' is not followed by whitespace.",
        "source": "com.puppycrawl.tools.checkstyle.checks.whitespace.WhitespaceAroundCheck"
    },
    {
        "line": "304",
        "column": "9",
        "severity": "warning",
        "message": "'{' at column 9 should be on the previous line.",
        "source": "com.puppycrawl.tools.checkstyle.checks.blocks.LeftCurlyCheck"
    },
    {
        "line": "306",
        "column": "66",
        "severity": "warning",
        "message": "',' is not followed by whitespace.",
        "source": "com.puppycrawl.tools.checkstyle.checks.whitespace.WhitespaceAfterCheck"
    },
    {
        "line": "306",
        "column": "81",
        "severity": "warning",
        "message": "',' is not followed by whitespace.",
        "source": "com.puppycrawl.tools.checkstyle.checks.whitespace.WhitespaceAfterCheck"
    },
    {
        "line": "308",
        "column": "16",
        "severity": "warning",
        "message": "'for' is not followed by whitespace.",
        "source": "com.puppycrawl.tools.checkstyle.checks.whitespace.WhitespaceAroundCheck"
    },
    {
        "line": "308",
        "column": "30",
        "severity": "warning",
        "message": "':' is not preceded with whitespace.",
        "source": "com.puppycrawl.tools.checkstyle.checks.whitespace.WhitespaceAroundCheck"
    },
    {
        "line": "315",
        "column": "28",
        "severity": "warning",
        "message": "',' is not followed by whitespace.",
        "source": "com.puppycrawl.tools.checkstyle.checks.whitespace.WhitespaceAfterCheck"
    },
    {
        "line": "317",
        "column": "19",
        "severity": "warning",
        "message": "'if' is not followed by whitespace.",
        "source": "com.puppycrawl.tools.checkstyle.checks.whitespace.WhitespaceAroundCheck"
    },
    {
        "line": "318",
        "column": "23",
        "severity": "warning",
        "message": "'if' is not followed by whitespace.",
        "source": "com.puppycrawl.tools.checkstyle.checks.whitespace.WhitespaceAroundCheck"
    },
    {
        "line": "319",
        "column": "21",
        "severity": "warning",
        "message": "'{' at column 21 should be on the previous line.",
        "source": "com.puppycrawl.tools.checkstyle.checks.blocks.LeftCurlyCheck"
    },
    {
        "line": "324",
        "column": "25",
        "severity": "warning",
        "message": "'else' is not followed by whitespace.",
        "source": "com.puppycrawl.tools.checkstyle.checks.whitespace.WhitespaceAroundCheck"
    },
    {
        "line": "324",
        "column": "25",
        "severity": "warning",
        "message": "'{' is not preceded with whitespace.",
        "source": "com.puppycrawl.tools.checkstyle.checks.whitespace.WhitespaceAroundCheck"
    },
    {
        "line": "331",
        "column": "15",
        "severity": "warning",
        "message": "'if' is not followed by whitespace.",
        "source": "com.puppycrawl.tools.checkstyle.checks.whitespace.WhitespaceAroundCheck"
    },
    {
        "line": "335",
        "column": "20",
        "severity": "warning",
        "message": "'for' is not followed by whitespace.",
        "source": "com.puppycrawl.tools.checkstyle.checks.whitespace.WhitespaceAroundCheck"
    },
    {
        "line": "335",
        "column": "26",
        "severity": "warning",
        "message": "'=' is not preceded with whitespace.",
        "source": "com.puppycrawl.tools.checkstyle.checks.whitespace.WhitespaceAroundCheck"
    },
    {
        "line": "335",
        "column": "27",
        "severity": "warning",
        "message": "'=' is not followed by whitespace.",
        "source": "com.puppycrawl.tools.checkstyle.checks.whitespace.WhitespaceAroundCheck"
    },
    {
        "line": "335",
        "column": "29",
        "severity": "warning",
        "message": "';' is not followed by whitespace.",
        "source": "com.puppycrawl.tools.checkstyle.checks.whitespace.WhitespaceAfterCheck"
    },
    {
        "line": "335",
        "column": "30",
        "severity": "warning",
        "message": "'<' is not preceded with whitespace.",
        "source": "com.puppycrawl.tools.checkstyle.checks.whitespace.WhitespaceAroundCheck"
    },
    {
        "line": "335",
        "column": "31",
        "severity": "warning",
        "message": "'<' is not followed by whitespace.",
        "source": "com.puppycrawl.tools.checkstyle.checks.whitespace.WhitespaceAroundCheck"
    },
    {
        "line": "335",
        "column": "33",
        "severity": "warning",
        "message": "';' is not followed by whitespace.",
        "source": "com.puppycrawl.tools.checkstyle.checks.whitespace.WhitespaceAfterCheck"
    },
    {
        "line": "371",
        "column": "13",
        "severity": "warning",
        "message": "Empty statement.",
        "source": "com.puppycrawl.tools.checkstyle.checks.coding.EmptyStatementCheck"
    },
    {
        "line": "383",
        "column": "49",
        "severity": "warning",
        "message": "',' is not followed by whitespace.",
        "source": "com.puppycrawl.tools.checkstyle.checks.whitespace.WhitespaceAfterCheck"
    },
    {
        "line": "391",
        "column": "13",
        "severity": "warning",
        "message": "Empty statement.",
        "source": "com.puppycrawl.tools.checkstyle.checks.coding.EmptyStatementCheck"
    },
    {
        "line": "398",
        "column": "20",
        "severity": "warning",
        "message": "',' is not followed by whitespace.",
        "source": "com.puppycrawl.tools.checkstyle.checks.whitespace.WhitespaceAfterCheck"
    },
    {
        "line": "400",
        "column": "9",
        "severity": "warning",
        "message": "'{' at column 9 should be on the previous line.",
        "source": "com.puppycrawl.tools.checkstyle.checks.blocks.LeftCurlyCheck"
    },
    {
        "line": "406",
        "column": "18",
        "severity": "warning",
        "message": "'while' is not followed by whitespace.",
        "source": "com.puppycrawl.tools.checkstyle.checks.whitespace.WhitespaceAroundCheck"
    },
    {
        "line": "407",
        "column": "13",
        "severity": "warning",
        "message": "'{' at column 13 should be on the previous line.",
        "source": "com.puppycrawl.tools.checkstyle.checks.blocks.LeftCurlyCheck"
    },
    {
        "line": "409",
        "column": "62",
        "severity": "warning",
        "message": "',' is not followed by whitespace.",
        "source": "com.puppycrawl.tools.checkstyle.checks.whitespace.WhitespaceAfterCheck"
    },
    {
        "line": "409",
        "column": "77",
        "severity": "warning",
        "message": "',' is not followed by whitespace.",
        "source": "com.puppycrawl.tools.checkstyle.checks.whitespace.WhitespaceAfterCheck"
    },
    {
        "line": "411",
        "column": "20",
        "severity": "warning",
        "message": "'for' is not followed by whitespace.",
        "source": "com.puppycrawl.tools.checkstyle.checks.whitespace.WhitespaceAroundCheck"
    },
    {
        "line": "411",
        "column": "34",
        "severity": "warning",
        "message": "':' is not preceded with whitespace.",
        "source": "com.puppycrawl.tools.checkstyle.checks.whitespace.WhitespaceAroundCheck"
    },
    {
        "line": "418",
        "column": "32",
        "severity": "warning",
        "message": "',' is not followed by whitespace.",
        "source": "com.puppycrawl.tools.checkstyle.checks.whitespace.WhitespaceAfterCheck"
    },
    {
        "line": "420",
        "column": "23",
        "severity": "warning",
        "message": "'if' is not followed by whitespace.",
        "source": "com.puppycrawl.tools.checkstyle.checks.whitespace.WhitespaceAroundCheck"
    },
    {
        "line": "427",
        "column": "19",
        "severity": "warning",
        "message": "'if' is not followed by whitespace.",
        "source": "com.puppycrawl.tools.checkstyle.checks.whitespace.WhitespaceAroundCheck"
    },
    {
        "line": "431",
        "column": "24",
        "severity": "warning",
        "message": "'for' is not followed by whitespace.",
        "source": "com.puppycrawl.tools.checkstyle.checks.whitespace.WhitespaceAroundCheck"
    },
    {
        "line": "431",
        "column": "30",
        "severity": "warning",
        "message": "'=' is not preceded with whitespace.",
        "source": "com.puppycrawl.tools.checkstyle.checks.whitespace.WhitespaceAroundCheck"
    },
    {
        "line": "431",
        "column": "31",
        "severity": "warning",
        "message": "'=' is not followed by whitespace.",
        "source": "com.puppycrawl.tools.checkstyle.checks.whitespace.WhitespaceAroundCheck"
    },
    {
        "line": "431",
        "column": "33",
        "severity": "warning",
        "message": "';' is not followed by whitespace.",
        "source": "com.puppycrawl.tools.checkstyle.checks.whitespace.WhitespaceAfterCheck"
    },
    {
        "line": "431",
        "column": "34",
        "severity": "warning",
        "message": "'<' is not preceded with whitespace.",
        "source": "com.puppycrawl.tools.checkstyle.checks.whitespace.WhitespaceAroundCheck"
    },
    {
        "line": "431",
        "column": "35",
        "severity": "warning",
        "message": "'<' is not followed by whitespace.",
        "source": "com.puppycrawl.tools.checkstyle.checks.whitespace.WhitespaceAroundCheck"
    },
    {
        "line": "431",
        "column": "37",
        "severity": "warning",
        "message": "';' is not followed by whitespace.",
        "source": "com.puppycrawl.tools.checkstyle.checks.whitespace.WhitespaceAfterCheck"
    },
    {
        "line": "445",
        "column": "29",
        "severity": "warning",
        "message": "Name 'storage_info' must match pattern '^[a-z][a-zA-Z0-9]*$'.",
        "source": "com.puppycrawl.tools.checkstyle.checks.naming.LocalVariableNameCheck"
    },
    {
        "line": "453",
        "column": "29",
        "severity": "warning",
        "message": "',' is not followed by whitespace.",
        "source": "com.puppycrawl.tools.checkstyle.checks.whitespace.WhitespaceAfterCheck"
    },
    {
        "line": "459",
        "column": "73",
        "severity": "warning",
        "message": "',' is not followed by whitespace.",
        "source": "com.puppycrawl.tools.checkstyle.checks.whitespace.WhitespaceAfterCheck"
    },
    {
        "line": "459",
        "column": "89",
        "severity": "warning",
        "message": "',' is not followed by whitespace.",
        "source": "com.puppycrawl.tools.checkstyle.checks.whitespace.WhitespaceAfterCheck"
    },
    {
        "line": "471",
        "column": "73",
        "severity": "warning",
        "message": "',' is not followed by whitespace.",
        "source": "com.puppycrawl.tools.checkstyle.checks.whitespace.WhitespaceAfterCheck"
    },
    {
        "line": "471",
        "column": "89",
        "severity": "warning",
        "message": "',' is not followed by whitespace.",
        "source": "com.puppycrawl.tools.checkstyle.checks.whitespace.WhitespaceAfterCheck"
    }
]