[
    {
        "line": "29",
        "column": "5",
        "severity": "error",
        "message": "Missing a Javadoc comment.",
        "source": "com.puppycrawl.tools.checkstyle.checks.javadoc.JavadocMethodCheck"
    },
    {
        "line": "32",
        "column": "5",
        "severity": "error",
        "message": "Missing a Javadoc comment.",
        "source": "com.puppycrawl.tools.checkstyle.checks.javadoc.JavadocMethodCheck"
    },
    {
        "line": "37",
        "column": "5",
        "severity": "error",
        "message": "Missing a Javadoc comment.",
        "source": "com.puppycrawl.tools.checkstyle.checks.javadoc.JavadocMethodCheck"
    },
    {
        "line": "42",
        "column": "5",
        "severity": "error",
        "message": "Missing a Javadoc comment.",
        "source": "com.puppycrawl.tools.checkstyle.checks.javadoc.JavadocMethodCheck"
    },
    {
        "line": "47",
        "column": "5",
        "severity": "error",
        "message": "Missing a Javadoc comment.",
        "source": "com.puppycrawl.tools.checkstyle.checks.javadoc.JavadocMethodCheck"
    },
    {
        "line": "52",
        "column": "5",
        "severity": "error",
        "message": "Missing a Javadoc comment.",
        "source": "com.puppycrawl.tools.checkstyle.checks.javadoc.JavadocMethodCheck"
    },
    {
        "line": "57",
        "column": "5",
        "severity": "error",
        "message": "Missing a Javadoc comment.",
        "source": "com.puppycrawl.tools.checkstyle.checks.javadoc.JavadocMethodCheck"
    },
    {
        "line": "62",
        "column": "5",
        "severity": "error",
        "message": "Missing a Javadoc comment.",
        "source": "com.puppycrawl.tools.checkstyle.checks.javadoc.JavadocMethodCheck"
    },
    {
        "line": "67",
        "column": "5",
        "severity": "error",
        "message": "Missing a Javadoc comment.",
        "source": "com.puppycrawl.tools.checkstyle.checks.javadoc.JavadocMethodCheck"
    },
    {
        "line": "72",
        "column": "5",
        "severity": "error",
        "message": "Missing a Javadoc comment.",
        "source": "com.puppycrawl.tools.checkstyle.checks.javadoc.JavadocMethodCheck"
    },
    {
        "line": "77",
        "column": "5",
        "severity": "error",
        "message": "Missing a Javadoc comment.",
        "source": "com.puppycrawl.tools.checkstyle.checks.javadoc.JavadocMethodCheck"
    },
    {
        "line": "78",
        "column": "17",
        "severity": "error",
        "message": "Name 'roundTripNitfFile2JP2_1place' must match pattern '^[a-z][a-zA-Z0-9]*$'.",
        "source": "com.puppycrawl.tools.checkstyle.checks.naming.MethodNameCheck"
    },
    {
        "line": "82",
        "column": "5",
        "severity": "error",
        "message": "Missing a Javadoc comment.",
        "source": "com.puppycrawl.tools.checkstyle.checks.javadoc.JavadocMethodCheck"
    },
    {
        "line": "83",
        "column": "17",
        "severity": "error",
        "message": "Name 'roundTripNitfFile2JP2_2places' must match pattern '^[a-z][a-zA-Z0-9]*$'.",
        "source": "com.puppycrawl.tools.checkstyle.checks.naming.MethodNameCheck"
    },
    {
        "line": "87",
        "column": "5",
        "severity": "error",
        "message": "Missing a Javadoc comment.",
        "source": "com.puppycrawl.tools.checkstyle.checks.javadoc.JavadocMethodCheck"
    },
    {
        "line": "92",
        "column": "5",
        "severity": "error",
        "message": "Missing a Javadoc comment.",
        "source": "com.puppycrawl.tools.checkstyle.checks.javadoc.JavadocMethodCheck"
    },
    {
        "line": "97",
        "column": "5",
        "severity": "error",
        "message": "Missing a Javadoc comment.",
        "source": "com.puppycrawl.tools.checkstyle.checks.javadoc.JavadocMethodCheck"
    },
    {
        "line": "102",
        "column": "5",
        "severity": "error",
        "message": "Missing a Javadoc comment.",
        "source": "com.puppycrawl.tools.checkstyle.checks.javadoc.JavadocMethodCheck"
    },
    {
        "line": "107",
        "column": "5",
        "severity": "error",
        "message": "Missing a Javadoc comment.",
        "source": "com.puppycrawl.tools.checkstyle.checks.javadoc.JavadocMethodCheck"
    },
    {
        "line": "112",
        "column": "5",
        "severity": "error",
        "message": "Missing a Javadoc comment.",
        "source": "com.puppycrawl.tools.checkstyle.checks.javadoc.JavadocMethodCheck"
    },
    {
        "line": "117",
        "column": "5",
        "severity": "error",
        "message": "Missing a Javadoc comment.",
        "source": "com.puppycrawl.tools.checkstyle.checks.javadoc.JavadocMethodCheck"
    },
    {
        "line": "122",
        "column": "5",
        "severity": "error",
        "message": "Missing a Javadoc comment.",
        "source": "com.puppycrawl.tools.checkstyle.checks.javadoc.JavadocMethodCheck"
    },
    {
        "line": "123",
        "column": "17",
        "severity": "error",
        "message": "Name 'roundTripNitfFile9JP2_1place' must match pattern '^[a-z][a-zA-Z0-9]*$'.",
        "source": "com.puppycrawl.tools.checkstyle.checks.naming.MethodNameCheck"
    },
    {
        "line": "127",
        "column": "5",
        "severity": "error",
        "message": "Missing a Javadoc comment.",
        "source": "com.puppycrawl.tools.checkstyle.checks.javadoc.JavadocMethodCheck"
    },
    {
        "line": "128",
        "column": "17",
        "severity": "error",
        "message": "Name 'roundTripNitfFile9JP2_2places' must match pattern '^[a-z][a-zA-Z0-9]*$'.",
        "source": "com.puppycrawl.tools.checkstyle.checks.naming.MethodNameCheck"
    },
    {
        "line": "132",
        "column": "5",
        "severity": "error",
        "message": "Missing a Javadoc comment.",
        "source": "com.puppycrawl.tools.checkstyle.checks.javadoc.JavadocMethodCheck"
    },
    {
        "line": "137",
        "column": "5",
        "severity": "error",
        "message": "Missing a Javadoc comment.",
        "source": "com.puppycrawl.tools.checkstyle.checks.javadoc.JavadocMethodCheck"
    },
    {
        "line": "141",
        "column": "5",
        "severity": "error",
        "message": "Missing a Javadoc comment.",
        "source": "com.puppycrawl.tools.checkstyle.checks.javadoc.JavadocMethodCheck"
    },
    {
        "line": "146",
        "column": "5",
        "severity": "error",
        "message": "Missing a Javadoc comment.",
        "source": "com.puppycrawl.tools.checkstyle.checks.javadoc.JavadocMethodCheck"
    },
    {
        "line": "151",
        "column": "5",
        "severity": "error",
        "message": "Missing a Javadoc comment.",
        "source": "com.puppycrawl.tools.checkstyle.checks.javadoc.JavadocMethodCheck"
    },
    {
        "line": "156",
        "column": "5",
        "severity": "error",
        "message": "Missing a Javadoc comment.",
        "source": "com.puppycrawl.tools.checkstyle.checks.javadoc.JavadocMethodCheck"
    },
    {
        "line": "161",
        "column": "5",
        "severity": "error",
        "message": "Missing a Javadoc comment.",
        "source": "com.puppycrawl.tools.checkstyle.checks.javadoc.JavadocMethodCheck"
    },
    {
        "line": "166",
        "column": "5",
        "severity": "error",
        "message": "Missing a Javadoc comment.",
        "source": "com.puppycrawl.tools.checkstyle.checks.javadoc.JavadocMethodCheck"
    },
    {
        "line": "171",
        "column": "5",
        "severity": "error",
        "message": "Missing a Javadoc comment.",
        "source": "com.puppycrawl.tools.checkstyle.checks.javadoc.JavadocMethodCheck"
    },
    {
        "line": "176",
        "column": "5",
        "severity": "error",
        "message": "Missing a Javadoc comment.",
        "source": "com.puppycrawl.tools.checkstyle.checks.javadoc.JavadocMethodCheck"
    },
    {
        "line": "181",
        "column": "5",
        "severity": "error",
        "message": "Missing a Javadoc comment.",
        "source": "com.puppycrawl.tools.checkstyle.checks.javadoc.JavadocMethodCheck"
    },
    {
        "line": "186",
        "column": "5",
        "severity": "error",
        "message": "Missing a Javadoc comment.",
        "source": "com.puppycrawl.tools.checkstyle.checks.javadoc.JavadocMethodCheck"
    },
    {
        "line": "191",
        "column": "5",
        "severity": "error",
        "message": "Missing a Javadoc comment.",
        "source": "com.puppycrawl.tools.checkstyle.checks.javadoc.JavadocMethodCheck"
    },
    {
        "line": "196",
        "column": "5",
        "severity": "error",
        "message": "Missing a Javadoc comment.",
        "source": "com.puppycrawl.tools.checkstyle.checks.javadoc.JavadocMethodCheck"
    },
    {
        "line": "201",
        "column": "5",
        "severity": "error",
        "message": "Missing a Javadoc comment.",
        "source": "com.puppycrawl.tools.checkstyle.checks.javadoc.JavadocMethodCheck"
    },
    {
        "line": "206",
        "column": "5",
        "severity": "error",
        "message": "Missing a Javadoc comment.",
        "source": "com.puppycrawl.tools.checkstyle.checks.javadoc.JavadocMethodCheck"
    },
    {
        "line": "211",
        "column": "5",
        "severity": "error",
        "message": "Missing a Javadoc comment.",
        "source": "com.puppycrawl.tools.checkstyle.checks.javadoc.JavadocMethodCheck"
    },
    {
        "line": "216",
        "column": "5",
        "severity": "error",
        "message": "Missing a Javadoc comment.",
        "source": "com.puppycrawl.tools.checkstyle.checks.javadoc.JavadocMethodCheck"
    },
    {
        "line": "221",
        "column": "5",
        "severity": "error",
        "message": "Missing a Javadoc comment.",
        "source": "com.puppycrawl.tools.checkstyle.checks.javadoc.JavadocMethodCheck"
    },
    {
        "line": "226",
        "column": "5",
        "severity": "error",
        "message": "Missing a Javadoc comment.",
        "source": "com.puppycrawl.tools.checkstyle.checks.javadoc.JavadocMethodCheck"
    },
    {
        "line": "231",
        "column": "5",
        "severity": "error",
        "message": "Missing a Javadoc comment.",
        "source": "com.puppycrawl.tools.checkstyle.checks.javadoc.JavadocMethodCheck"
    },
    {
        "line": "236",
        "column": "5",
        "severity": "error",
        "message": "Missing a Javadoc comment.",
        "source": "com.puppycrawl.tools.checkstyle.checks.javadoc.JavadocMethodCheck"
    },
    {
        "line": "241",
        "column": "5",
        "severity": "error",
        "message": "Missing a Javadoc comment.",
        "source": "com.puppycrawl.tools.checkstyle.checks.javadoc.JavadocMethodCheck"
    },
    {
        "line": "246",
        "column": "5",
        "severity": "error",
        "message": "Missing a Javadoc comment.",
        "source": "com.puppycrawl.tools.checkstyle.checks.javadoc.JavadocMethodCheck"
    }
]