[
    {
        "line": "18",
        "severity": "error",
        "message": "Missing a Javadoc comment.",
        "source": "com.puppycrawl.tools.checkstyle.checks.javadoc.JavadocTypeCheck"
    },
    {
        "line": "35",
        "column": "9",
        "severity": "warning",
        "message": "Missing a Javadoc comment.",
        "source": "com.puppycrawl.tools.checkstyle.checks.javadoc.JavadocMethodCheck"
    },
    {
        "line": "37",
        "column": "72",
        "severity": "info",
        "message": "'2016' is a magic number.",
        "source": "com.puppycrawl.tools.checkstyle.checks.coding.MagicNumberCheck"
    },
    {
        "line": "38",
        "column": "78",
        "severity": "info",
        "message": "'2016' is a magic number.",
        "source": "com.puppycrawl.tools.checkstyle.checks.coding.MagicNumberCheck"
    },
    {
        "line": "39",
        "column": "82",
        "severity": "info",
        "message": "'2016' is a magic number.",
        "source": "com.puppycrawl.tools.checkstyle.checks.coding.MagicNumberCheck"
    },
    {
        "line": "41",
        "column": "80",
        "severity": "info",
        "message": "'2016' is a magic number.",
        "source": "com.puppycrawl.tools.checkstyle.checks.coding.MagicNumberCheck"
    },
    {
        "line": "45",
        "column": "86",
        "severity": "info",
        "message": "'2016' is a magic number.",
        "source": "com.puppycrawl.tools.checkstyle.checks.coding.MagicNumberCheck"
    },
    {
        "line": "49",
        "column": "90",
        "severity": "info",
        "message": "'2016' is a magic number.",
        "source": "com.puppycrawl.tools.checkstyle.checks.coding.MagicNumberCheck"
    },
    {
        "line": "80",
        "column": "9",
        "severity": "warning",
        "message": "Missing a Javadoc comment.",
        "source": "com.puppycrawl.tools.checkstyle.checks.javadoc.JavadocMethodCheck"
    },
    {
        "line": "86",
        "column": "9",
        "severity": "warning",
        "message": "Missing a Javadoc comment.",
        "source": "com.puppycrawl.tools.checkstyle.checks.javadoc.JavadocMethodCheck"
    },
    {
        "line": "95",
        "column": "9",
        "severity": "warning",
        "message": "Missing a Javadoc comment.",
        "source": "com.puppycrawl.tools.checkstyle.checks.javadoc.JavadocMethodCheck"
    },
    {
        "line": "102",
        "column": "9",
        "severity": "warning",
        "message": "Missing a Javadoc comment.",
        "source": "com.puppycrawl.tools.checkstyle.checks.javadoc.JavadocMethodCheck"
    },
    {
        "line": "112",
        "column": "9",
        "severity": "warning",
        "message": "Missing a Javadoc comment.",
        "source": "com.puppycrawl.tools.checkstyle.checks.javadoc.JavadocMethodCheck"
    },
    {
        "line": "122",
        "column": "9",
        "severity": "warning",
        "message": "Missing a Javadoc comment.",
        "source": "com.puppycrawl.tools.checkstyle.checks.javadoc.JavadocMethodCheck"
    },
    {
        "line": "131",
        "column": "9",
        "severity": "warning",
        "message": "Missing a Javadoc comment.",
        "source": "com.puppycrawl.tools.checkstyle.checks.javadoc.JavadocMethodCheck"
    },
    {
        "line": "149",
        "column": "9",
        "severity": "warning",
        "message": "Missing a Javadoc comment.",
        "source": "com.puppycrawl.tools.checkstyle.checks.javadoc.JavadocMethodCheck"
    },
    {
        "line": "157",
        "column": "9",
        "severity": "warning",
        "message": "Missing a Javadoc comment.",
        "source": "com.puppycrawl.tools.checkstyle.checks.javadoc.JavadocMethodCheck"
    },
    {
        "line": "165",
        "column": "9",
        "severity": "warning",
        "message": "Missing a Javadoc comment.",
        "source": "com.puppycrawl.tools.checkstyle.checks.javadoc.JavadocMethodCheck"
    },
    {
        "line": "173",
        "column": "9",
        "severity": "warning",
        "message": "Missing a Javadoc comment.",
        "source": "com.puppycrawl.tools.checkstyle.checks.javadoc.JavadocMethodCheck"
    },
    {
        "line": "182",
        "column": "9",
        "severity": "warning",
        "message": "Missing a Javadoc comment.",
        "source": "com.puppycrawl.tools.checkstyle.checks.javadoc.JavadocMethodCheck"
    },
    {
        "line": "189",
        "column": "9",
        "severity": "warning",
        "message": "Missing a Javadoc comment.",
        "source": "com.puppycrawl.tools.checkstyle.checks.javadoc.JavadocMethodCheck"
    },
    {
        "line": "196",
        "column": "9",
        "severity": "warning",
        "message": "Missing a Javadoc comment.",
        "source": "com.puppycrawl.tools.checkstyle.checks.javadoc.JavadocMethodCheck"
    }
]