[
    {
        "line": "80",
        "severity": "warning",
        "message": "Line is longer than 100 characters (found 110).",
        "source": "com.puppycrawl.tools.checkstyle.checks.sizes.LineLengthCheck"
    },
    {
        "line": "389",
        "severity": "warning",
        "message": "Line is longer than 100 characters (found 112).",
        "source": "com.puppycrawl.tools.checkstyle.checks.sizes.LineLengthCheck"
    },
    {
        "line": "673",
        "severity": "warning",
        "message": "Line is longer than 100 characters (found 106).",
        "source": "com.puppycrawl.tools.checkstyle.checks.sizes.LineLengthCheck"
    },
    {
        "line": "676",
        "severity": "warning",
        "message": "Line is longer than 100 characters (found 119).",
        "source": "com.puppycrawl.tools.checkstyle.checks.sizes.LineLengthCheck"
    },
    {
        "line": "677",
        "severity": "warning",
        "message": "Line is longer than 100 characters (found 104).",
        "source": "com.puppycrawl.tools.checkstyle.checks.sizes.LineLengthCheck"
    },
    {
        "line": "680",
        "severity": "warning",
        "message": "Line is longer than 100 characters (found 120).",
        "source": "com.puppycrawl.tools.checkstyle.checks.sizes.LineLengthCheck"
    }
]