[
    {
        "line": "3",
        "severity": "error",
        "message": "Line does not match expected header line of ' \\* contributor license agreements.  See the NOTICE file distributed with'.",
        "source": "com.puppycrawl.tools.checkstyle.checks.header.RegexpHeaderCheck"
    },
    {
        "line": "22",
        "severity": "warning",
        "message": "Wrong order for 'java.util.ArrayList' import.",
        "source": "com.puppycrawl.tools.checkstyle.checks.imports.ImportOrderCheck"
    },
    {
        "line": "27",
        "severity": "warning",
        "message": "'org.apache.usergrid.persistence.collection.CollectionScope' should be separated from previous imports.",
        "source": "com.puppycrawl.tools.checkstyle.checks.imports.ImportOrderCheck"
    },
    {
        "line": "30",
        "severity": "warning",
        "message": "Wrong order for 'org.apache.usergrid.persistence.collection.guice.MigrationManagerRule' import.",
        "source": "com.puppycrawl.tools.checkstyle.checks.imports.ImportOrderCheck"
    },
    {
        "line": "44",
        "severity": "warning",
        "message": "Wrong order for 'org.apache.usergrid.persistence.index.query.EntityRef' import.",
        "source": "com.puppycrawl.tools.checkstyle.checks.imports.ImportOrderCheck"
    },
    {
        "line": "49",
        "severity": "warning",
        "message": "'org.jukito.JukitoRunner' should be separated from previous imports.",
        "source": "com.puppycrawl.tools.checkstyle.checks.imports.ImportOrderCheck"
    },
    {
        "line": "51",
        "severity": "warning",
        "message": "'org.junit.Assert.assertEquals' should be separated from previous imports.",
        "source": "com.puppycrawl.tools.checkstyle.checks.imports.ImportOrderCheck"
    },
    {
        "line": "53",
        "severity": "warning",
        "message": "Wrong order for 'org.junit.ClassRule' import.",
        "source": "com.puppycrawl.tools.checkstyle.checks.imports.ImportOrderCheck"
    },
    {
        "line": "62",
        "severity": "warning",
        "message": "Annotation style must be 'COMPACT_NO_ARRAY'.",
        "source": "com.puppycrawl.tools.checkstyle.checks.annotation.AnnotationUseStyleCheck"
    },
    {
        "line": "75",
        "severity": "warning",
        "message": "Line has trailing spaces.",
        "source": "com.puppycrawl.tools.checkstyle.checks.regexp.RegexpSinglelineCheck"
    },
    {
        "line": "84",
        "severity": "warning",
        "message": "Line has trailing spaces.",
        "source": "com.puppycrawl.tools.checkstyle.checks.regexp.RegexpSinglelineCheck"
    },
    {
        "line": "107",
        "column": "1",
        "severity": "error",
        "message": "Line contains a tab character.",
        "source": "com.puppycrawl.tools.checkstyle.checks.whitespace.FileTabCharacterCheck"
    },
    {
        "line": "111",
        "column": "1",
        "severity": "error",
        "message": "Line contains a tab character.",
        "source": "com.puppycrawl.tools.checkstyle.checks.whitespace.FileTabCharacterCheck"
    },
    {
        "line": "112",
        "column": "1",
        "severity": "error",
        "message": "Line contains a tab character.",
        "source": "com.puppycrawl.tools.checkstyle.checks.whitespace.FileTabCharacterCheck"
    },
    {
        "line": "113",
        "severity": "warning",
        "message": "Line has trailing spaces.",
        "source": "com.puppycrawl.tools.checkstyle.checks.regexp.RegexpSinglelineCheck"
    },
    {
        "line": "113",
        "column": "1",
        "severity": "error",
        "message": "Line contains a tab character.",
        "source": "com.puppycrawl.tools.checkstyle.checks.whitespace.FileTabCharacterCheck"
    },
    {
        "line": "123",
        "severity": "warning",
        "message": "Line has trailing spaces.",
        "source": "com.puppycrawl.tools.checkstyle.checks.regexp.RegexpSinglelineCheck"
    },
    {
        "line": "123",
        "column": "1",
        "severity": "error",
        "message": "Line contains a tab character.",
        "source": "com.puppycrawl.tools.checkstyle.checks.whitespace.FileTabCharacterCheck"
    },
    {
        "line": "126",
        "column": "1",
        "severity": "error",
        "message": "Line contains a tab character.",
        "source": "com.puppycrawl.tools.checkstyle.checks.whitespace.FileTabCharacterCheck"
    },
    {
        "line": "130",
        "column": "1",
        "severity": "error",
        "message": "Line contains a tab character.",
        "source": "com.puppycrawl.tools.checkstyle.checks.whitespace.FileTabCharacterCheck"
    },
    {
        "line": "131",
        "severity": "warning",
        "message": "Line has trailing spaces.",
        "source": "com.puppycrawl.tools.checkstyle.checks.regexp.RegexpSinglelineCheck"
    },
    {
        "line": "131",
        "column": "1",
        "severity": "error",
        "message": "Line contains a tab character.",
        "source": "com.puppycrawl.tools.checkstyle.checks.whitespace.FileTabCharacterCheck"
    },
    {
        "line": "132",
        "column": "1",
        "severity": "error",
        "message": "Line contains a tab character.",
        "source": "com.puppycrawl.tools.checkstyle.checks.whitespace.FileTabCharacterCheck"
    },
    {
        "line": "133",
        "column": "1",
        "severity": "error",
        "message": "Line contains a tab character.",
        "source": "com.puppycrawl.tools.checkstyle.checks.whitespace.FileTabCharacterCheck"
    },
    {
        "line": "136",
        "column": "1",
        "severity": "error",
        "message": "Line contains a tab character.",
        "source": "com.puppycrawl.tools.checkstyle.checks.whitespace.FileTabCharacterCheck"
    },
    {
        "line": "137",
        "severity": "warning",
        "message": "Line has trailing spaces.",
        "source": "com.puppycrawl.tools.checkstyle.checks.regexp.RegexpSinglelineCheck"
    },
    {
        "line": "137",
        "column": "1",
        "severity": "error",
        "message": "Line contains a tab character.",
        "source": "com.puppycrawl.tools.checkstyle.checks.whitespace.FileTabCharacterCheck"
    },
    {
        "line": "138",
        "column": "1",
        "severity": "error",
        "message": "Line contains a tab character.",
        "source": "com.puppycrawl.tools.checkstyle.checks.whitespace.FileTabCharacterCheck"
    },
    {
        "line": "139",
        "column": "1",
        "severity": "error",
        "message": "Line contains a tab character.",
        "source": "com.puppycrawl.tools.checkstyle.checks.whitespace.FileTabCharacterCheck"
    },
    {
        "line": "142",
        "severity": "warning",
        "message": "Line has trailing spaces.",
        "source": "com.puppycrawl.tools.checkstyle.checks.regexp.RegexpSinglelineCheck"
    },
    {
        "line": "142",
        "column": "1",
        "severity": "error",
        "message": "Line contains a tab character.",
        "source": "com.puppycrawl.tools.checkstyle.checks.whitespace.FileTabCharacterCheck"
    },
    {
        "line": "143",
        "severity": "warning",
        "message": "Line has trailing spaces.",
        "source": "com.puppycrawl.tools.checkstyle.checks.regexp.RegexpSinglelineCheck"
    },
    {
        "line": "144",
        "column": "1",
        "severity": "error",
        "message": "Line contains a tab character.",
        "source": "com.puppycrawl.tools.checkstyle.checks.whitespace.FileTabCharacterCheck"
    },
    {
        "line": "148",
        "severity": "warning",
        "message": "Line has trailing spaces.",
        "source": "com.puppycrawl.tools.checkstyle.checks.regexp.RegexpSinglelineCheck"
    },
    {
        "line": "148",
        "column": "1",
        "severity": "error",
        "message": "Line contains a tab character.",
        "source": "com.puppycrawl.tools.checkstyle.checks.whitespace.FileTabCharacterCheck"
    },
    {
        "line": "149",
        "severity": "warning",
        "message": "Line has trailing spaces.",
        "source": "com.puppycrawl.tools.checkstyle.checks.regexp.RegexpSinglelineCheck"
    },
    {
        "line": "149",
        "column": "1",
        "severity": "error",
        "message": "Line contains a tab character.",
        "source": "com.puppycrawl.tools.checkstyle.checks.whitespace.FileTabCharacterCheck"
    },
    {
        "line": "150",
        "column": "1",
        "severity": "error",
        "message": "Line contains a tab character.",
        "source": "com.puppycrawl.tools.checkstyle.checks.whitespace.FileTabCharacterCheck"
    },
    {
        "line": "151",
        "column": "1",
        "severity": "error",
        "message": "Line contains a tab character.",
        "source": "com.puppycrawl.tools.checkstyle.checks.whitespace.FileTabCharacterCheck"
    },
    {
        "line": "154",
        "column": "1",
        "severity": "error",
        "message": "Line contains a tab character.",
        "source": "com.puppycrawl.tools.checkstyle.checks.whitespace.FileTabCharacterCheck"
    },
    {
        "line": "159",
        "column": "1",
        "severity": "error",
        "message": "Line contains a tab character.",
        "source": "com.puppycrawl.tools.checkstyle.checks.whitespace.FileTabCharacterCheck"
    },
    {
        "line": "160",
        "severity": "warning",
        "message": "Line has trailing spaces.",
        "source": "com.puppycrawl.tools.checkstyle.checks.regexp.RegexpSinglelineCheck"
    },
    {
        "line": "160",
        "column": "1",
        "severity": "error",
        "message": "Line contains a tab character.",
        "source": "com.puppycrawl.tools.checkstyle.checks.whitespace.FileTabCharacterCheck"
    },
    {
        "line": "161",
        "column": "1",
        "severity": "error",
        "message": "Line contains a tab character.",
        "source": "com.puppycrawl.tools.checkstyle.checks.whitespace.FileTabCharacterCheck"
    },
    {
        "line": "162",
        "column": "1",
        "severity": "error",
        "message": "Line contains a tab character.",
        "source": "com.puppycrawl.tools.checkstyle.checks.whitespace.FileTabCharacterCheck"
    },
    {
        "line": "166",
        "severity": "warning",
        "message": "Line has trailing spaces.",
        "source": "com.puppycrawl.tools.checkstyle.checks.regexp.RegexpSinglelineCheck"
    },
    {
        "line": "166",
        "column": "1",
        "severity": "error",
        "message": "Line contains a tab character.",
        "source": "com.puppycrawl.tools.checkstyle.checks.whitespace.FileTabCharacterCheck"
    },
    {
        "line": "167",
        "column": "1",
        "severity": "error",
        "message": "Line contains a tab character.",
        "source": "com.puppycrawl.tools.checkstyle.checks.whitespace.FileTabCharacterCheck"
    },
    {
        "line": "168",
        "column": "1",
        "severity": "error",
        "message": "Line contains a tab character.",
        "source": "com.puppycrawl.tools.checkstyle.checks.whitespace.FileTabCharacterCheck"
    },
    {
        "line": "173",
        "column": "9",
        "severity": "error",
        "message": "Line contains a tab character.",
        "source": "com.puppycrawl.tools.checkstyle.checks.whitespace.FileTabCharacterCheck"
    },
    {
        "line": "174",
        "column": "9",
        "severity": "error",
        "message": "Line contains a tab character.",
        "source": "com.puppycrawl.tools.checkstyle.checks.whitespace.FileTabCharacterCheck"
    },
    {
        "line": "175",
        "column": "1",
        "severity": "error",
        "message": "Line contains a tab character.",
        "source": "com.puppycrawl.tools.checkstyle.checks.whitespace.FileTabCharacterCheck"
    },
    {
        "line": "176",
        "column": "1",
        "severity": "error",
        "message": "Line contains a tab character.",
        "source": "com.puppycrawl.tools.checkstyle.checks.whitespace.FileTabCharacterCheck"
    },
    {
        "line": "177",
        "severity": "warning",
        "message": "Line has trailing spaces.",
        "source": "com.puppycrawl.tools.checkstyle.checks.regexp.RegexpSinglelineCheck"
    },
    {
        "line": "177",
        "column": "1",
        "severity": "error",
        "message": "Line contains a tab character.",
        "source": "com.puppycrawl.tools.checkstyle.checks.whitespace.FileTabCharacterCheck"
    },
    {
        "line": "178",
        "column": "1",
        "severity": "error",
        "message": "Line contains a tab character.",
        "source": "com.puppycrawl.tools.checkstyle.checks.whitespace.FileTabCharacterCheck"
    },
    {
        "line": "179",
        "column": "1",
        "severity": "error",
        "message": "Line contains a tab character.",
        "source": "com.puppycrawl.tools.checkstyle.checks.whitespace.FileTabCharacterCheck"
    },
    {
        "line": "182",
        "severity": "warning",
        "message": "Line has trailing spaces.",
        "source": "com.puppycrawl.tools.checkstyle.checks.regexp.RegexpSinglelineCheck"
    },
    {
        "line": "185",
        "severity": "warning",
        "message": "Line has trailing spaces.",
        "source": "com.puppycrawl.tools.checkstyle.checks.regexp.RegexpSinglelineCheck"
    },
    {
        "line": "185",
        "column": "1",
        "severity": "error",
        "message": "Line contains a tab character.",
        "source": "com.puppycrawl.tools.checkstyle.checks.whitespace.FileTabCharacterCheck"
    },
    {
        "line": "186",
        "column": "1",
        "severity": "error",
        "message": "Line contains a tab character.",
        "source": "com.puppycrawl.tools.checkstyle.checks.whitespace.FileTabCharacterCheck"
    },
    {
        "line": "187",
        "column": "1",
        "severity": "error",
        "message": "Line contains a tab character.",
        "source": "com.puppycrawl.tools.checkstyle.checks.whitespace.FileTabCharacterCheck"
    },
    {
        "line": "192",
        "severity": "warning",
        "message": "Line has trailing spaces.",
        "source": "com.puppycrawl.tools.checkstyle.checks.regexp.RegexpSinglelineCheck"
    },
    {
        "line": "192",
        "column": "1",
        "severity": "error",
        "message": "Line contains a tab character.",
        "source": "com.puppycrawl.tools.checkstyle.checks.whitespace.FileTabCharacterCheck"
    },
    {
        "line": "193",
        "column": "1",
        "severity": "error",
        "message": "Line contains a tab character.",
        "source": "com.puppycrawl.tools.checkstyle.checks.whitespace.FileTabCharacterCheck"
    },
    {
        "line": "194",
        "column": "1",
        "severity": "error",
        "message": "Line contains a tab character.",
        "source": "com.puppycrawl.tools.checkstyle.checks.whitespace.FileTabCharacterCheck"
    },
    {
        "line": "195",
        "severity": "warning",
        "message": "Line has trailing spaces.",
        "source": "com.puppycrawl.tools.checkstyle.checks.regexp.RegexpSinglelineCheck"
    },
    {
        "line": "195",
        "column": "1",
        "severity": "error",
        "message": "Line contains a tab character.",
        "source": "com.puppycrawl.tools.checkstyle.checks.whitespace.FileTabCharacterCheck"
    },
    {
        "line": "201",
        "severity": "warning",
        "message": "Line has trailing spaces.",
        "source": "com.puppycrawl.tools.checkstyle.checks.regexp.RegexpSinglelineCheck"
    },
    {
        "line": "201",
        "column": "1",
        "severity": "error",
        "message": "Line contains a tab character.",
        "source": "com.puppycrawl.tools.checkstyle.checks.whitespace.FileTabCharacterCheck"
    },
    {
        "line": "202",
        "column": "1",
        "severity": "error",
        "message": "Line contains a tab character.",
        "source": "com.puppycrawl.tools.checkstyle.checks.whitespace.FileTabCharacterCheck"
    },
    {
        "line": "203",
        "column": "1",
        "severity": "error",
        "message": "Line contains a tab character.",
        "source": "com.puppycrawl.tools.checkstyle.checks.whitespace.FileTabCharacterCheck"
    },
    {
        "line": "216",
        "severity": "warning",
        "message": "Line has trailing spaces.",
        "source": "com.puppycrawl.tools.checkstyle.checks.regexp.RegexpSinglelineCheck"
    },
    {
        "line": "216",
        "column": "1",
        "severity": "error",
        "message": "Line contains a tab character.",
        "source": "com.puppycrawl.tools.checkstyle.checks.whitespace.FileTabCharacterCheck"
    },
    {
        "line": "217",
        "column": "1",
        "severity": "error",
        "message": "Line contains a tab character.",
        "source": "com.puppycrawl.tools.checkstyle.checks.whitespace.FileTabCharacterCheck"
    },
    {
        "line": "218",
        "column": "1",
        "severity": "error",
        "message": "Line contains a tab character.",
        "source": "com.puppycrawl.tools.checkstyle.checks.whitespace.FileTabCharacterCheck"
    },
    {
        "line": "236",
        "column": "1",
        "severity": "error",
        "message": "Line contains a tab character.",
        "source": "com.puppycrawl.tools.checkstyle.checks.whitespace.FileTabCharacterCheck"
    },
    {
        "line": "281",
        "severity": "warning",
        "message": "Line has trailing spaces.",
        "source": "com.puppycrawl.tools.checkstyle.checks.regexp.RegexpSinglelineCheck"
    },
    {
        "line": "368",
        "severity": "warning",
        "message": "Line has trailing spaces.",
        "source": "com.puppycrawl.tools.checkstyle.checks.regexp.RegexpSinglelineCheck"
    },
    {
        "line": "401",
        "severity": "warning",
        "message": "Line has trailing spaces.",
        "source": "com.puppycrawl.tools.checkstyle.checks.regexp.RegexpSinglelineCheck"
    },
    {
        "line": "472",
        "severity": "warning",
        "message": "Line has trailing spaces.",
        "source": "com.puppycrawl.tools.checkstyle.checks.regexp.RegexpSinglelineCheck"
    },
    {
        "line": "503",
        "severity": "warning",
        "message": "Line has trailing spaces.",
        "source": "com.puppycrawl.tools.checkstyle.checks.regexp.RegexpSinglelineCheck"
    },
    {
        "line": "587",
        "column": "1",
        "severity": "error",
        "message": "Line contains a tab character.",
        "source": "com.puppycrawl.tools.checkstyle.checks.whitespace.FileTabCharacterCheck"
    }
]